sourcerandom
