Metadata-Version: 2.1
Name: sourcerandom
Version: 1.0.2
Summary: Python package for alternate true random number generator using sources provided by either TRNG online services, plaintext uint8 files (separated by whitespace) or collections of ints.
Home-page: https://github.com/Yard1/sourcerandom
Author: Antoni Baum
Author-email: antoni.baum@protonmail.com
License: MIT
Platform: UNKNOWN
Classifier: License :: OSI Approved :: MIT License
Classifier: Programming Language :: Python
Classifier: Programming Language :: Python :: 3
Classifier: Programming Language :: Python :: 3.5
Classifier: Programming Language :: Python :: 3.6
Classifier: Programming Language :: Python :: Implementation :: CPython
Classifier: Programming Language :: Python :: Implementation :: PyPy
Classifier: Operating System :: OS Independent
Classifier: Development Status :: 4 - Beta
Requires-Python: >=3.5.2
